{
  "deathlyplays": -18,
  "insist": 386,
  "speckeldorft": 40,
  "nightcraven": 62,
  "thememes69": 2,
  "volco": 65,
  "bronze0re": 83,
  "kairak": 16,
  "sukesha": 0,
  "mewth": 582,
  "maxlos": 6,
  "jigglykong": 20,
  "suhhhh": 6,
  "flxtch": 4,
  "9ft": 13,
  "backatmyday": 41,
  "hoeenhero": 28,
  "wobbleleez": 26,
  "sparkychild": 2,
  "crystalludicolo": 0,
  "apexwobz": 3,
  "fiftynine": 16,
  "ashleythepikachu": 39,
  "c733937123": 73,
  "earlofkarp": 3,
  "omegawobz": 7,
  "shadowoflord": 1,
  "perison": 151,
  "iflexy": 6,
  "foreword": 8,
  "greenlandfire": 31,
  "oppose": 1,
  "config": 17,
  "imnotspamming": 1,
  "megas4ever": 106,
  "vxn": -825,
  "cuticles": 1,
  "linkcode": 11,
  "ub03xurkitree": 4,
  "alfastorm": 69,
  "stellation": 18,
  "frainthatcher": 1,
  "greenlandwater": 13,
  "execute": 52,
  "yeahexactly": 1,
  "lefrenchpancakes": 3,
  "darknightskies": 7,
  "nitro62": 1,
  "cate": 7,
  "aeonlucid": 14,
  "theresort": 10,
  "starf0x": 6,
  "ripnormal": 1,
  "haxorus04": 26,
  "revivalwobz": 11,
  "marshoul": 13,
  "mystifi": 10,
  "migglebank": 1,
  "preign": 15,
  "glameowch": 6,
  "crystalludicolo1": 0,
  "stellations": 1,
  "jchris308": 21,
  "desokoro": 1,
  "thegodofpie": 19,
  "md5": 1,
  "travisci": 1,
  "spriterscash": 90,
  "bulbsaur": 20,
  "handyhelper": 2,
  "megadiancie16": 2,
  "diancie11": 2,
  "c73397123": 0,
  "eelek": -52,
  "eelektrossbot": 13,
  "wonderchoose": 13,
  "thepyrope": 4,
  "lemewthies": 1,
  "bloodedkitten": 20,
  "kimisumi": 10,
  "hapoop": 1,
  "": 0,
  "beeky": 0,
  "cat4cyclone": 5,
  "cyt0pl4sm": 53,
  "bandedlunala": 1,
  "jumbowhales": 1,
  "yasuo": 4,
  "lordcoldwraith": 39,
  "mosmero": 44,
  "youngcarti": 14,
  "reallifesand": 2,
  "pokemonmasterrosin": 10,
  "nightofschiffer": 12,
  "kadu3520": 10,
  "tonygames": 61,
  "raichugamer": 2,
  "lukasgamer56": 117,
  "druzinhobr": 2,
  "neveronline": 1,
  "kiladin": 2,
  "capitaogeneralll": 6,
  "phoenixard": 2,
  "chandie": 121,
  "lttenthelegend": 5,
  "seventywalk622": 10,
  "mateus135": 9,
  "mcgreninja": 12,
  "lucaskiritoxbr": 4,
  "007nilo": 29,
  "headfactory": 22,
  "playershadowbr": 29,
  "magicohappy": 42,
  "kiritoreibreaker": 0,
  "almightybronzong": 23,
  "guiltasbr": 71,
  "funtymes": 21,
  "zryan77": 2,
  "garchompvgc": 1,
  "ggdaca": 36,
  "noviex": 9,
  "zryanxdt": 12,
  "xpra": 3,
  "failures": 30,
  "horrific17": 22,
  "shrektd": 53,
  "smashbrosbad": 3,
  "friedrice353": 43,
  "johnnydragneel": 3,
  "snakerl": 22,
  "teecko": 0,
  "tiosloth": 22,
  "a1sciz": 7,
  "chesnaught90000": 3,
  "ilordznightmare": 13,
  "dileer": 4,
  "serverbott": 8,
  "flemme": 0,
  "creamggshowdown": 1,
  "vinnygamer": 5,
  "drevon": 35,
  "charizard230": 41,
  "abhrasaha": 4,
  "completeamateur": 5,
  "ashketchumkallos": 0,
  "mickjewel": 2,
  "algoz33br": 13,
  "decidueyegamerbr": 8,
  "hamsandwich335": 7,
  "litebluyoshi": 5,
  "meltymoltengalaxy": 19,
  "pikachusuperfoda": 1,
  "deaddeadpool": 1,
  "phistorm": 1,
  "subsist": 1,
  "eelekt": 1,
  "vacuo": 9,
  "shukesha": 10,
  "flufi": 2,
  "ablone": 1,
  "malgrim": 32,
  "garotogx": 83,
  "iaplanets": 38,
  "vuze": 2,
  "tomlaurent": 0,
  "almightyjudgment": 91,
  "shadowmasterrosin": 0,
  "epsilon101": 5,
  "eeleks": 1,
  "gizmolives0n": 1,
  "gabrielhjbs": 2,
  "trueheroqs": 31,
  "beldumdaleks": 1,
  "slipperysoap": 1,
  "lolkeklmao": 20,
  "ablone5": 4,
  "revivalpyronian": 13,
  "revivalspirit": 3,
  "kevso": 437,
  "bricadeira": 4,
  "cacklettassoul": 2,
  "princessteddiursa": 36,
  "cosmicsaiyanscaris": 1,
  "renfur": 101,
  "joshykun": 2,
  "stumbles23": 1,
  "exiledserver": 5,
  "dunn4": 10,
  "beekiestlariat": 2,
  "dodofofo": 11,
  "dtv603": 10,
  "kanekiplayerbr": 56,
  "revivalpsychosis": 3,
  "murkytorrent": 25,
  "testersgersfv": -20,
  "testersfersfv": 0,
  "elfey": 1,
  "mefistofles": 3,
  "rebel0313": 1,
  "virninha": 10,
  "damecco": 26,
  "fevered": 5,
  "q1987": 1,
  "volcos": 8,
  "finny": 24,
  "tediursamajor": 1,
  "twentyonestarlys": 1,
  "omegahades1": 33,
  "douglasgamer": 0,
  "grainne": 1,
  "maddypink7": 20,
  "revivalsnow": 1,
  "sashaway": 14,
  "alphashivam": 8,
  "snowwolf3000": 10,
  "scepthesceptaile": 30,
  "joaovictorbrmito": 31,
  "hitmonlee007": 15,
  "eron3": 3,
  "redgrasswesson": 18,
  "wasabababe": 2,
  "arashicage": 1,
  "infallible": 1,
  "nomorewrds": 8,
  "theexiler": 59,
  "oblivionprince": 1,
  "joaopedrogamer": 1,
  "megaplayerbr": 2,
  "25thlightofheaven": 13,
  "m4theusgamerbr": 11,
  "mimikyujp": 5,
  "lecs": 4,
  "ashocampeao": 4,
  "exiler": 3,
  "borutosayajin": 12,
  "biabrgamer": 8,
  "rubirulez": 2,
  "guipepi": 3,
  "datguyblaziken": 1,
  "oblivionfurret": 67,
  "censorious": 3,
  "cynsylveon": 1,
  "autisticmewtwo": 1,
  "tsardragon": 37,
  "cytoscards": 0,
  "cytocards": 0,
  "aalolanhaunter": 2,
  "bluetails2k": 1,
  "prolobolo": 1,
  "alphamojie": 14,
  "irenerv": 27,
  "prince": 2,
  "floweryarnyoshi": 8,
  "gabrielefofinha": 13,
  "triston217": 2,
  "humanoplayer": 2,
  "scurpuffmay": 5,
  "redarrowmaster": 0,
  "serjuf": 21,
  "philmiester": 2,
  "awug": 0,
  "o3o": 1,
  "cynthesylveon": 3,
  "piscean": 10,
  "hydrostatics": 4,
  "ashketchumalolaa": 0,
  "druzinhobru": 11,
  "metapodharden": 37,
  "geosaber": 2,
  "possibilities": 12,
  "ricardoyuuki2000": 4,
  "mylesken": 15,
  "blackim": 17,
  "alfoj": 1,
  "diabeetuses": 1,
  "emgglunown": 8,
  "a1char": 3,
  "chilidawg12": 1,
  "ub01symbi0nt": 30,
  "wizoark": 2,
  "keinherz": 16,
  "victor6467": 7,
  "corazan": 4,
  "ghig": 14,
  "ranfen": 14,
  "tejas10": 7,
  "nineage": 7,
  "universalcraftr": 11,
  "c7": 7,
  "etrons": 7,
  "echosierra": 40,
  "naisha29": 7,
  "alpico": 7,
  "theganesh": 7,
  "legacysaffron": 7,
  "jackburke1012": 2,
  "shinybr": 0,
  "tyamya": 19,
  "inisst": -372,
  "inist": -372,
  "notdns": 2,
  "saitochi": 7,
  "rikegamerbrex": 2,
  "rikebreakerbrex": 6,
  "haakunite": 4,
  "redgamesbrex": 7,
  "raropop": 0,
  "unownman": 7,
  "danchu": 2,
  "leaderwattson": 7,
  "twiinis": 9,
  "blacrya": 7
}